ticsummary_sochi/__init__.py
ticsummary_sochi/__main__.py
ticsummary_sochi/backWorking.py
ticsummary_sochi/callibrationGalo.py
ticsummary_sochi/dataTIC.py
ticsummary_sochi/dataWriter.py
ticsummary_sochi/handlerData.py
ticsummary_sochi/inputDataHandler.py
ticsummary_sochi/modeShowData.py
ticsummary_sochi/model.py
ticsummary_sochi/mysql.py
ticsummary_sochi/readerCSV.py
ticsummary_sochi/readerFiles.py
ticsummary_sochi/resources/__init__.py
ticsummary_sochi/resources/images/__init__.py
ticsummary_sochi/ui/__init__.py
ticsummary_sochi/ui/dialogCalibrationGalo.py
ticsummary_sochi/ui/galoBeam.py
ticsummary_sochi/ui/mainWindow.py
ticsummary_sochi/ui/profileBeamDock.py
ticsummary_sochi/ui/serverParametersDialog.py
ticsummary_sochi/ui/settingsColorBarDialog.py
ticsummary_sochi/ui/viewGraphicsDialog.py
ticsummary_sochi/ui/uic/__init__.py
ticsummary_sochi/ui/uic/connectServer.ui
ticsummary_sochi/ui/uic/dialogCalibrationGalo.ui
ticsummary_sochi/ui/uic/mainWindow.ui
ticsummary_sochi/ui/uic/settingsColorBarDialog.ui
ticsummary_sochi/ui/uic/viewGraphics.ui
neofti_ticsummary_sochi-0.0.32.dist-info/METADATA
neofti_ticsummary_sochi-0.0.32.dist-info/WHEEL
neofti_ticsummary_sochi-0.0.32.dist-info/entry_points.txt
neofti_ticsummary_sochi-0.0.32.dist-info/top_level.txt
neofti_ticsummary_sochi-0.0.32.dist-info/RECORD
